[
  {
    "LINE_NUM": "05호선",
    "FR_CODE": "551",
    "STATION_CD": "2552",
    "STATION_NM": "명일",
    "TRAIN_NO": "5001",
    "ARRIVETIME": "05:50:20",
    "LEFTTIME": "05:50:50",
    "ORIGINSTATION": "2545",
    "DESTSTATION": "2566",
    "SUBWAYSNAME": "군자",
    "SUBWAYENAME": "하남검단산",
    "WEEK_TAG": "2",
    "INOUT_TAG": "2",
    "FL_FLAG": "",
    "DESTSTATION2": "",
    "EXPRESS_YN": "G",
    "BRANCH_LINE": ""
  },
  {
    "LINE_NUM": "05호선",
    "FR_CODE": "551",
    "STATION_CD": "2552",
    "STATION_NM": "명일",
    "TRAIN_NO": "5003",
    "ARRIVETIME": "06:05:20",
    "LEFTTIME": "06:05:50",
    "ORIGINSTATION": "2541",
    "DESTSTATION": "2566",
    "SUBWAYSNAME": "왕십리",
    "SUBWAYENAME": "하남검단산",
    "WEEK_TAG": "2",
    "INOUT_TAG": "2",
    "FL_FLAG": "",
    "DESTSTATION2": "",
    "EXPRESS_YN": "G",
    "BRANCH_LINE": ""
  },
  {
    "LINE_NUM": "05호선",
    "FR_CODE": "551",
    "STATION_CD": "2552",
    "STATION_NM": "명일",
    "TRAIN_NO": "5005",
    "ARRIVETIME": "06:22:50",
    "LEFTTIME": "06:23:20",
    "ORIGINSTATION": "2549",
    "DESTSTATION": "2566",
    "SUBWAYSNAME": "강동",
    "SUBWAYENAME": "하남검단산",
    "WEEK_TAG": "2",
    "INOUT_TAG": "2",
    "FL_FLAG": "",
    "DESTSTATION2": "",
    "EXPRESS_YN": "G",
    "BRANCH_LINE": ""
  },
  {
    "LINE_NUM": "05호선",
    "FR_CODE": "551",
    "STATION_CD": "2552",
    "STATION_NM": "명일",
    "TRAIN_NO": "5007",
    "ARRIVETIME": "06:34:20",
    "LEFTTIME": "06:34:50",
    "ORIGINSTATION": "2518",
    "DESTSTATION": "2566",
    "SUBWAYSNAME": "화곡",
    "SUBWAYENAME": "하남검단산",
    "WEEK_TAG": "2",
    "INOUT_TAG": "2",
    "FL_FLAG": "",
    "DESTSTATION2": "",
    "EXPRESS_YN": "G",
    "BRANCH_LINE": ""
  },
  {
    "LINE_NUM": "05호선",
    "FR_CODE": "551",
    "STATION_CD": "2552",
    "STATION_NM": "명일",
    "TRAIN_NO": "5009",
    "ARRIVETIME": "06:49:10",
    "LEFTTIME": "06:49:40",
    "ORIGINSTATION": "2511",
    "DESTSTATION": "2566",
    "SUBWAYSNAME": "방화",
    "SUBWAYENAME": "하남검단산",
    "WEEK_TAG": "2",
    "INOUT_TAG": "2",
    "FL_FLAG": "",
    "DESTSTATION2": "",
    "EXPRESS_YN": "G",
    "BRANCH_LINE": ""
  },
  {
    "LINE_NUM": "05호선",
    "FR_CODE": "551",
    "STATION_CD": "2552",
    "STATION_NM": "명일",
    "TRAIN_NO": "5011",
    "ARRIVETIME": "07:04:10",
    "LEFTTIME": "07:04:40",
    "ORIGINSTATION": "2511",
    "DESTSTATION": "2566",
    "SUBWAYSNAME": "방화",
    "SUBWAYENAME": "하남검단산",
    "WEEK_TAG": "2",
    "INOUT_TAG": "2",
    "FL_FLAG": "",
    "DESTSTATION2": "",
    "EXPRESS_YN": "G",
    "BRANCH_LINE": ""
  },
  {
    "LINE_NUM": "05호선",
    "FR_CODE": "551",
    "STATION_CD": "2552",
    "STATION_NM": "명일",
    "TRAIN_NO": "5013",
    "ARRIVETIME": "07:18:10",
    "LEFTTIME": "07:18:40",
    "ORIGINSTATION": "2511",
    "DESTSTATION": "2566",
    "SUBWAYSNAME": "방화",
    "SUBWAYENAME": "하남검단산",
    "WEEK_TAG": "2",
    "INOUT_TAG": "2",
    "FL_FLAG": "",
    "DESTSTATION2": "",
    "EXPRESS_YN": "G",
    "BRANCH_LINE": ""
  },
  {
    "LINE_NUM": "05호선",
    "FR_CODE": "551",
    "STATION_CD": "2552",
    "STATION_NM": "명일",
    "TRAIN_NO": "5015",
    "ARRIVETIME": "07:32:10",
    "LEFTTIME": "07:32:40",
    "ORIGINSTATION": "2511",
    "DESTSTATION": "2566",
    "SUBWAYSNAME": "방화",
    "SUBWAYENAME": "하남검단산",
    "WEEK_TAG": "2",
    "INOUT_TAG": "2",
    "FL_FLAG": "",
    "DESTSTATION2": "",
    "EXPRESS_YN": "G",
    "BRANCH_LINE": ""
  },
  {
    "LINE_NUM": "05호선",
    "FR_CODE": "551",
    "STATION_CD": "2552",
    "STATION_NM": "명일",
    "TRAIN_NO": "5017",
    "ARRIVETIME": "07:46:10",
    "LEFTTIME": "07:46:40",
    "ORIGINSTATION": "2511",
    "DESTSTATION": "2566",
    "SUBWAYSNAME": "방화",
    "SUBWAYENAME": "하남검단산",
    "WEEK_TAG": "2",
    "INOUT_TAG": "2",
    "FL_FLAG": "",
    "DESTSTATION2": "",
    "EXPRESS_YN": "G",
    "BRANCH_LINE": ""
  },
  {
    "LINE_NUM": "05호선",
    "FR_CODE": "551",
    "STATION_CD": "2552",
    "STATION_NM": "명일",
    "TRAIN_NO": "5019",
    "ARRIVETIME": "07:54:50",
    "LEFTTIME": "07:55:20",
    "ORIGINSTATION": "2549",
    "DESTSTATION": "2566",
    "SUBWAYSNAME": "강동",
    "SUBWAYENAME": "하남검단산",
    "WEEK_TAG": "2",
    "INOUT_TAG": "2",
    "FL_FLAG": "",
    "DESTSTATION2": "",
    "EXPRESS_YN": "G",
    "BRANCH_LINE": ""
  },
  {
    "LINE_NUM": "05호선",
    "FR_CODE": "551",
    "STATION_CD": "2552",
    "STATION_NM": "명일",
    "TRAIN_NO": "5021",
    "ARRIVETIME": "08:00:10",
    "LEFTTIME": "08:00:40",
    "ORIGINSTATION": "2511",
    "DESTSTATION": "2554",
    "SUBWAYSNAME": "방화",
    "SUBWAYENAME": "상일동",
    "WEEK_TAG": "2",
    "INOUT_TAG": "2",
    "FL_FLAG": "",
    "DESTSTATION2": "",
    "EXPRESS_YN": "G",
    "BRANCH_LINE": ""
  },
  {
    "LINE_NUM": "05호선",
    "FR_CODE": "551",
    "STATION_CD": "2552",
    "STATION_NM": "명일",
    "TRAIN_NO": "5023",
    "ARRIVETIME": "08:14:10",
    "LEFTTIME": "08:14:40",
    "ORIGINSTATION": "2511",
    "DESTSTATION": "2566",
    "SUBWAYSNAME": "방화",
    "SUBWAYENAME": "하남검단산",
    "WEEK_TAG": "2",
    "INOUT_TAG": "2",
    "FL_FLAG": "",
    "DESTSTATION2": "",
    "EXPRESS_YN": "G",
    "BRANCH_LINE": ""
  },
  {
    "LINE_NUM": "05호선",
    "FR_CODE": "551",
    "STATION_CD": "2552",
    "STATION_NM": "명일",
    "TRAIN_NO": "5025",
    "ARRIVETIME": "08:27:40",
    "LEFTTIME": "08:28:10",
    "ORIGINSTATION": "2511",
    "DESTSTATION": "2566",
    "SUBWAYSNAME": "방화",
    "SUBWAYENAME": "하남검단산",
    "WEEK_TAG": "2",
    "INOUT_TAG": "2",
    "FL_FLAG": "",
    "DESTSTATION2": "",
    "EXPRESS_YN": "G",
    "BRANCH_LINE": ""
  },
  {
    "LINE_NUM": "05호선",
    "FR_CODE": "551",
    "STATION_CD": "2552",
    "STATION_NM": "명일",
    "TRAIN_NO": "5027",
    "ARRIVETIME": "08:40:40",
    "LEFTTIME": "08:41:10",
    "ORIGINSTATION": "2511",
    "DESTSTATION": "2566",
    "SUBWAYSNAME": "방화",
    "SUBWAYENAME": "하남검단산",
    "WEEK_TAG": "2",
    "INOUT_TAG": "2",
    "FL_FLAG": "",
    "DESTSTATION2": "",
    "EXPRESS_YN": "G",
    "BRANCH_LINE": ""
  },
  {
    "LINE_NUM": "05호선",
    "FR_CODE": "551",
    "STATION_CD": "2552",
    "STATION_NM": "명일",
    "TRAIN_NO": "5029",
    "ARRIVETIME": "08:53:40",
    "LEFTTIME": "08:54:10",
    "ORIGINSTATION": "2511",
    "DESTSTATION": "2566",
    "SUBWAYSNAME": "방화",
    "SUBWAYENAME": "하남검단산",
    "WEEK_TAG": "2",
    "INOUT_TAG": "2",
    "FL_FLAG": "",
    "DESTSTATION2": "",
    "EXPRESS_YN": "G",
    "BRANCH_LINE": ""
  },
  {
    "LINE_NUM": "05호선",
    "FR_CODE": "551",
    "STATION_CD": "2552",
    "STATION_NM": "명일",
    "TRAIN_NO": "5031",
    "ARRIVETIME": "09:06:40",
    "LEFTTIME": "09:07:10",
    "ORIGINSTATION": "2511",
    "DESTSTATION": "2566",
    "SUBWAYSNAME": "방화",
    "SUBWAYENAME": "하남검단산",
    "WEEK_TAG": "2",
    "INOUT_TAG": "2",
    "FL_FLAG": "",
    "DESTSTATION2": "",
    "EXPRESS_YN": "G",
    "BRANCH_LINE": ""
  },
  {
    "LINE_NUM": "05호선",
    "FR_CODE": "551",
    "STATION_CD": "2552",
    "STATION_NM": "명일",
    "TRAIN_NO": "5033",
    "ARRIVETIME": "09:19:40",
    "LEFTTIME": "09:20:10",
    "ORIGINSTATION": "2511",
    "DESTSTATION": "2566",
    "SUBWAYSNAME": "방화",
    "SUBWAYENAME": "하남검단산",
    "WEEK_TAG": "2",
    "INOUT_TAG": "2",
    "FL_FLAG": "",
    "DESTSTATION2": "",
    "EXPRESS_YN": "G",
    "BRANCH_LINE": ""
  },
  {
    "LINE_NUM": "05호선",
    "FR_CODE": "551",
    "STATION_CD": "2552",
    "STATION_NM": "명일",
    "TRAIN_NO": "5035",
    "ARRIVETIME": "09:32:40",
    "LEFTTIME": "09:33:10",
    "ORIGINSTATION": "2511",
    "DESTSTATION": "2566",
    "SUBWAYSNAME": "방화",
    "SUBWAYENAME": "하남검단산",
    "WEEK_TAG": "2",
    "INOUT_TAG": "2",
    "FL_FLAG": "",
    "DESTSTATION2": "",
    "EXPRESS_YN": "G",
    "BRANCH_LINE": ""
  },
  {
    "LINE_NUM": "05호선",
    "FR_CODE": "551",
    "STATION_CD": "2552",
    "STATION_NM": "명일",
    "TRAIN_NO": "5037",
    "ARRIVETIME": "09:40:50",
    "LEFTTIME": "09:41:20",
    "ORIGINSTATION": "2549",
    "DESTSTATION": "2566",
    "SUBWAYSNAME": "강동",
    "SUBWAYENAME": "하남검단산",
    "WEEK_TAG": "2",
    "INOUT_TAG": "2",
    "FL_FLAG": "",
    "DESTSTATION2": "",
    "EXPRESS_YN": "G",
    "BRANCH_LINE": ""
  },
  {
    "LINE_NUM": "05호선",
    "FR_CODE": "551",
    "STATION_CD": "2552",
    "STATION_NM": "명일",
    "TRAIN_NO": "5039",
    "ARRIVETIME": "09:45:40",
    "LEFTTIME": "09:46:10",
    "ORIGINSTATION": "2511",
    "DESTSTATION": "2554",
    "SUBWAYSNAME": "방화",
    "SUBWAYENAME": "상일동",
    "WEEK_TAG": "2",
    "INOUT_TAG": "2",
    "FL_FLAG": "",
    "DESTSTATION2": "",
    "EXPRESS_YN": "G",
    "BRANCH_LINE": ""
  },
  {
    "LINE_NUM": "05호선",
    "FR_CODE": "551",
    "STATION_CD": "2552",
    "STATION_NM": "명일",
    "TRAIN_NO": "5041",
    "ARRIVETIME": "09:58:40",
    "LEFTTIME": "09:59:10",
    "ORIGINSTATION": "2511",
    "DESTSTATION": "2566",
    "SUBWAYSNAME": "방화",
    "SUBWAYENAME": "하남검단산",
    "WEEK_TAG": "2",
    "INOUT_TAG": "2",
    "FL_FLAG": "",
    "DESTSTATION2": "",
    "EXPRESS_YN": "G",
    "BRANCH_LINE": ""
  },
  {
    "LINE_NUM": "05호선",
    "FR_CODE": "551",
    "STATION_CD": "2552",
    "STATION_NM": "명일",
    "TRAIN_NO": "5043",
    "ARRIVETIME": "10:11:40",
    "LEFTTIME": "10:12:10",
    "ORIGINSTATION": "2511",
    "DESTSTATION": "2566",
    "SUBWAYSNAME": "방화",
    "SUBWAYENAME": "하남검단산",
    "WEEK_TAG": "2",
    "INOUT_TAG": "2",
    "FL_FLAG": "",
    "DESTSTATION2": "",
    "EXPRESS_YN": "G",
    "BRANCH_LINE": ""
  },
  {
    "LINE_NUM": "05호선",
    "FR_CODE": "551",
    "STATION_CD": "2552",
    "STATION_NM": "명일",
    "TRAIN_NO": "5045",
    "ARRIVETIME": "10:24:40",
    "LEFTTIME": "10:25:10",
    "ORIGINSTATION": "2511",
    "DESTSTATION": "2566",
    "SUBWAYSNAME": "방화",
    "SUBWAYENAME": "하남검단산",
    "WEEK_TAG": "2",
    "INOUT_TAG": "2",
    "FL_FLAG": "",
    "DESTSTATION2": "",
    "EXPRESS_YN": "G",
    "BRANCH_LINE": ""
  },
  {
    "LINE_NUM": "05호선",
    "FR_CODE": "551",
    "STATION_CD": "2552",
    "STATION_NM": "명일",
    "TRAIN_NO": "5047",
    "ARRIVETIME": "10:37:40",
    "LEFTTIME": "10:38:10",
    "ORIGINSTATION": "2511",
    "DESTSTATION": "2566",
    "SUBWAYSNAME": "방화",
    "SUBWAYENAME": "하남검단산",
    "WEEK_TAG": "2",
    "INOUT_TAG": "2",
    "FL_FLAG": "",
    "DESTSTATION2": "",
    "EXPRESS_YN": "G",
    "BRANCH_LINE": ""
  },
  {
    "LINE_NUM": "05호선",
    "FR_CODE": "551",
    "STATION_CD": "2552",
    "STATION_NM": "명일",
    "TRAIN_NO": "5049",
    "ARRIVETIME": "10:50:40",
    "LEFTTIME": "10:51:10",
    "ORIGINSTATION": "2511",
    "DESTSTATION": "2566",
    "SUBWAYSNAME": "방화",
    "SUBWAYENAME": "하남검단산",
    "WEEK_TAG": "2",
    "INOUT_TAG": "2",
    "FL_FLAG": "",
    "DESTSTATION2": "",
    "EXPRESS_YN": "G",
    "BRANCH_LINE": ""
  },
  {
    "LINE_NUM": "05호선",
    "FR_CODE": "551",
    "STATION_CD": "2552",
    "STATION_NM": "명일",
    "TRAIN_NO": "5051",
    "ARRIVETIME": "11:03:40",
    "LEFTTIME": "11:04:10",
    "ORIGINSTATION": "2511",
    "DESTSTATION": "2566",
    "SUBWAYSNAME": "방화",
    "SUBWAYENAME": "하남검단산",
    "WEEK_TAG": "2",
    "INOUT_TAG": "2",
    "FL_FLAG": "",
    "DESTSTATION2": "",
    "EXPRESS_YN": "G",
    "BRANCH_LINE": ""
  },
  {
    "LINE_NUM": "05호선",
    "FR_CODE": "551",
    "STATION_CD": "2552",
    "STATION_NM": "명일",
    "TRAIN_NO": "5053",
    "ARRIVETIME": "11:16:40",
    "LEFTTIME": "11:17:10",
    "ORIGINSTATION": "2511",
    "DESTSTATION": "2566",
    "SUBWAYSNAME": "방화",
    "SUBWAYENAME": "하남검단산",
    "WEEK_TAG": "2",
    "INOUT_TAG": "2",
    "FL_FLAG": "",
    "DESTSTATION2": "",
    "EXPRESS_YN": "G",
    "BRANCH_LINE": ""
  },
  {
    "LINE_NUM": "05호선",
    "FR_CODE": "551",
    "STATION_CD": "2552",
    "STATION_NM": "명일",
    "TRAIN_NO": "5055",
    "ARRIVETIME": "11:29:40",
    "LEFTTIME": "11:30:10",
    "ORIGINSTATION": "2511",
    "DESTSTATION": "2566",
    "SUBWAYSNAME": "방화",
    "SUBWAYENAME": "하남검단산",
    "WEEK_TAG": "2",
    "INOUT_TAG": "2",
    "FL_FLAG": "",
    "DESTSTATION2": "",
    "EXPRESS_YN": "G",
    "BRANCH_LINE": ""
  },
  {
    "LINE_NUM": "05호선",
    "FR_CODE": "551",
    "STATION_CD": "2552",
    "STATION_NM": "명일",
    "TRAIN_NO": "5057",
    "ARRIVETIME": "11:42:40",
    "LEFTTIME": "11:43:10",
    "ORIGINSTATION": "2511",
    "DESTSTATION": "2566",
    "SUBWAYSNAME": "방화",
    "SUBWAYENAME": "하남검단산",
    "WEEK_TAG": "2",
    "INOUT_TAG": "2",
    "FL_FLAG": "",
    "DESTSTATION2": "",
    "EXPRESS_YN": "G",
    "BRANCH_LINE": ""
  },
  {
    "LINE_NUM": "05호선",
    "FR_CODE": "551",
    "STATION_CD": "2552",
    "STATION_NM": "명일",
    "TRAIN_NO": "5059",
    "ARRIVETIME": "11:55:40",
    "LEFTTIME": "11:56:10",
    "ORIGINSTATION": "2511",
    "DESTSTATION": "2566",
    "SUBWAYSNAME": "방화",
    "SUBWAYENAME": "하남검단산",
    "WEEK_TAG": "2",
    "INOUT_TAG": "2",
    "FL_FLAG": "",
    "DESTSTATION2": "",
    "EXPRESS_YN": "G",
    "BRANCH_LINE": ""
  },
  {
    "LINE_NUM": "05호선",
    "FR_CODE": "551",
    "STATION_CD": "2552",
    "STATION_NM": "명일",
    "TRAIN_NO": "5061",
    "ARRIVETIME": "12:08:40",
    "LEFTTIME": "12:09:10",
    "ORIGINSTATION": "2511",
    "DESTSTATION": "2566",
    "SUBWAYSNAME": "방화",
    "SUBWAYENAME": "하남검단산",
    "WEEK_TAG": "2",
    "INOUT_TAG": "2",
    "FL_FLAG": "",
    "DESTSTATION2": "",
    "EXPRESS_YN": "G",
    "BRANCH_LINE": ""
  },
  {
    "LINE_NUM": "05호선",
    "FR_CODE": "551",
    "STATION_CD": "2552",
    "STATION_NM": "명일",
    "TRAIN_NO": "5063",
    "ARRIVETIME": "12:21:40",
    "LEFTTIME": "12:22:10",
    "ORIGINSTATION": "2511",
    "DESTSTATION": "2566",
    "SUBWAYSNAME": "방화",
    "SUBWAYENAME": "하남검단산",
    "WEEK_TAG": "2",
    "INOUT_TAG": "2",
    "FL_FLAG": "",
    "DESTSTATION2": "",
    "EXPRESS_YN": "G",
    "BRANCH_LINE": ""
  },
  {
    "LINE_NUM": "05호선",
    "FR_CODE": "551",
    "STATION_CD": "2552",
    "STATION_NM": "명일",
    "TRAIN_NO": "5065",
    "ARRIVETIME": "12:34:40",
    "LEFTTIME": "12:35:10",
    "ORIGINSTATION": "2511",
    "DESTSTATION": "2566",
    "SUBWAYSNAME": "방화",
    "SUBWAYENAME": "하남검단산",
    "WEEK_TAG": "2",
    "INOUT_TAG": "2",
    "FL_FLAG": "",
    "DESTSTATION2": "",
    "EXPRESS_YN": "G",
    "BRANCH_LINE": ""
  },
  {
    "LINE_NUM": "05호선",
    "FR_CODE": "551",
    "STATION_CD": "2552",
    "STATION_NM": "명일",
    "TRAIN_NO": "5067",
    "ARRIVETIME": "12:47:40",
    "LEFTTIME": "12:48:10",
    "ORIGINSTATION": "2511",
    "DESTSTATION": "2566",
    "SUBWAYSNAME": "방화",
    "SUBWAYENAME": "하남검단산",
    "WEEK_TAG": "2",
    "INOUT_TAG": "2",
    "FL_FLAG": "",
    "DESTSTATION2": "",
    "EXPRESS_YN": "G",
    "BRANCH_LINE": ""
  },
  {
    "LINE_NUM": "05호선",
    "FR_CODE": "551",
    "STATION_CD": "2552",
    "STATION_NM": "명일",
    "TRAIN_NO": "5069",
    "ARRIVETIME": "13:00:40",
    "LEFTTIME": "13:01:10",
    "ORIGINSTATION": "2511",
    "DESTSTATION": "2566",
    "SUBWAYSNAME": "방화",
    "SUBWAYENAME": "하남검단산",
    "WEEK_TAG": "2",
    "INOUT_TAG": "2",
    "FL_FLAG": "",
    "DESTSTATION2": "",
    "EXPRESS_YN": "G",
    "BRANCH_LINE": ""
  },
  {
    "LINE_NUM": "05호선",
    "FR_CODE": "551",
    "STATION_CD": "2552",
    "STATION_NM": "명일",
    "TRAIN_NO": "5071",
    "ARRIVETIME": "13:13:40",
    "LEFTTIME": "13:14:10",
    "ORIGINSTATION": "2511",
    "DESTSTATION": "2566",
    "SUBWAYSNAME": "방화",
    "SUBWAYENAME": "하남검단산",
    "WEEK_TAG": "2",
    "INOUT_TAG": "2",
    "FL_FLAG": "",
    "DESTSTATION2": "",
    "EXPRESS_YN": "G",
    "BRANCH_LINE": ""
  },
  {
    "LINE_NUM": "05호선",
    "FR_CODE": "551",
    "STATION_CD": "2552",
    "STATION_NM": "명일",
    "TRAIN_NO": "5073",
    "ARRIVETIME": "13:26:40",
    "LEFTTIME": "13:27:10",
    "ORIGINSTATION": "2511",
    "DESTSTATION": "2566",
    "SUBWAYSNAME": "방화",
    "SUBWAYENAME": "하남검단산",
    "WEEK_TAG": "2",
    "INOUT_TAG": "2",
    "FL_FLAG": "",
    "DESTSTATION2": "",
    "EXPRESS_YN": "G",
    "BRANCH_LINE": ""
  },
  {
    "LINE_NUM": "05호선",
    "FR_CODE": "551",
    "STATION_CD": "2552",
    "STATION_NM": "명일",
    "TRAIN_NO": "5075",
    "ARRIVETIME": "13:39:40",
    "LEFTTIME": "13:40:10",
    "ORIGINSTATION": "2511",
    "DESTSTATION": "2566",
    "SUBWAYSNAME": "방화",
    "SUBWAYENAME": "하남검단산",
    "WEEK_TAG": "2",
    "INOUT_TAG": "2",
    "FL_FLAG": "",
    "DESTSTATION2": "",
    "EXPRESS_YN": "G",
    "BRANCH_LINE": ""
  },
  {
    "LINE_NUM": "05호선",
    "FR_CODE": "551",
    "STATION_CD": "2552",
    "STATION_NM": "명일",
    "TRAIN_NO": "5077",
    "ARRIVETIME": "13:52:40",
    "LEFTTIME": "13:53:10",
    "ORIGINSTATION": "2511",
    "DESTSTATION": "2566",
    "SUBWAYSNAME": "방화",
    "SUBWAYENAME": "하남검단산",
    "WEEK_TAG": "2",
    "INOUT_TAG": "2",
    "FL_FLAG": "",
    "DESTSTATION2": "",
    "EXPRESS_YN": "G",
    "BRANCH_LINE": ""
  },
  {
    "LINE_NUM": "05호선",
    "FR_CODE": "551",
    "STATION_CD": "2552",
    "STATION_NM": "명일",
    "TRAIN_NO": "5079",
    "ARRIVETIME": "14:05:40",
    "LEFTTIME": "14:06:10",
    "ORIGINSTATION": "2511",
    "DESTSTATION": "2566",
    "SUBWAYSNAME": "방화",
    "SUBWAYENAME": "하남검단산",
    "WEEK_TAG": "2",
    "INOUT_TAG": "2",
    "FL_FLAG": "",
    "DESTSTATION2": "",
    "EXPRESS_YN": "G",
    "BRANCH_LINE": ""
  },
  {
    "LINE_NUM": "05호선",
    "FR_CODE": "551",
    "STATION_CD": "2552",
    "STATION_NM": "명일",
    "TRAIN_NO": "5081",
    "ARRIVETIME": "14:18:40",
    "LEFTTIME": "14:19:10",
    "ORIGINSTATION": "2511",
    "DESTSTATION": "2566",
    "SUBWAYSNAME": "방화",
    "SUBWAYENAME": "하남검단산",
    "WEEK_TAG": "2",
    "INOUT_TAG": "2",
    "FL_FLAG": "",
    "DESTSTATION2": "",
    "EXPRESS_YN": "G",
    "BRANCH_LINE": ""
  },
  {
    "LINE_NUM": "05호선",
    "FR_CODE": "551",
    "STATION_CD": "2552",
    "STATION_NM": "명일",
    "TRAIN_NO": "5083",
    "ARRIVETIME": "14:31:40",
    "LEFTTIME": "14:32:10",
    "ORIGINSTATION": "2511",
    "DESTSTATION": "2566",
    "SUBWAYSNAME": "방화",
    "SUBWAYENAME": "하남검단산",
    "WEEK_TAG": "2",
    "INOUT_TAG": "2",
    "FL_FLAG": "",
    "DESTSTATION2": "",
    "EXPRESS_YN": "G",
    "BRANCH_LINE": ""
  },
  {
    "LINE_NUM": "05호선",
    "FR_CODE": "551",
    "STATION_CD": "2552",
    "STATION_NM": "명일",
    "TRAIN_NO": "5085",
    "ARRIVETIME": "14:44:40",
    "LEFTTIME": "14:45:10",
    "ORIGINSTATION": "2511",
    "DESTSTATION": "2566",
    "SUBWAYSNAME": "방화",
    "SUBWAYENAME": "하남검단산",
    "WEEK_TAG": "2",
    "INOUT_TAG": "2",
    "FL_FLAG": "",
    "DESTSTATION2": "",
    "EXPRESS_YN": "G",
    "BRANCH_LINE": ""
  },
  {
    "LINE_NUM": "05호선",
    "FR_CODE": "551",
    "STATION_CD": "2552",
    "STATION_NM": "명일",
    "TRAIN_NO": "5087",
    "ARRIVETIME": "14:57:40",
    "LEFTTIME": "14:58:10",
    "ORIGINSTATION": "2511",
    "DESTSTATION": "2566",
    "SUBWAYSNAME": "방화",
    "SUBWAYENAME": "하남검단산",
    "WEEK_TAG": "2",
    "INOUT_TAG": "2",
    "FL_FLAG": "",
    "DESTSTATION2": "",
    "EXPRESS_YN": "G",
    "BRANCH_LINE": ""
  },
  {
    "LINE_NUM": "05호선",
    "FR_CODE": "551",
    "STATION_CD": "2552",
    "STATION_NM": "명일",
    "TRAIN_NO": "5089",
    "ARRIVETIME": "15:10:40",
    "LEFTTIME": "15:11:10",
    "ORIGINSTATION": "2511",
    "DESTSTATION": "2566",
    "SUBWAYSNAME": "방화",
    "SUBWAYENAME": "하남검단산",
    "WEEK_TAG": "2",
    "INOUT_TAG": "2",
    "FL_FLAG": "",
    "DESTSTATION2": "",
    "EXPRESS_YN": "G",
    "BRANCH_LINE": ""
  },
  {
    "LINE_NUM": "05호선",
    "FR_CODE": "551",
    "STATION_CD": "2552",
    "STATION_NM": "명일",
    "TRAIN_NO": "5091",
    "ARRIVETIME": "15:23:40",
    "LEFTTIME": "15:24:10",
    "ORIGINSTATION": "2511",
    "DESTSTATION": "2566",
    "SUBWAYSNAME": "방화",
    "SUBWAYENAME": "하남검단산",
    "WEEK_TAG": "2",
    "INOUT_TAG": "2",
    "FL_FLAG": "",
    "DESTSTATION2": "",
    "EXPRESS_YN": "G",
    "BRANCH_LINE": ""
  },
  {
    "LINE_NUM": "05호선",
    "FR_CODE": "551",
    "STATION_CD": "2552",
    "STATION_NM": "명일",
    "TRAIN_NO": "5093",
    "ARRIVETIME": "15:36:40",
    "LEFTTIME": "15:37:10",
    "ORIGINSTATION": "2511",
    "DESTSTATION": "2566",
    "SUBWAYSNAME": "방화",
    "SUBWAYENAME": "하남검단산",
    "WEEK_TAG": "2",
    "INOUT_TAG": "2",
    "FL_FLAG": "",
    "DESTSTATION2": "",
    "EXPRESS_YN": "G",
    "BRANCH_LINE": ""
  },
  {
    "LINE_NUM": "05호선",
    "FR_CODE": "551",
    "STATION_CD": "2552",
    "STATION_NM": "명일",
    "TRAIN_NO": "5095",
    "ARRIVETIME": "15:49:40",
    "LEFTTIME": "15:50:10",
    "ORIGINSTATION": "2511",
    "DESTSTATION": "2566",
    "SUBWAYSNAME": "방화",
    "SUBWAYENAME": "하남검단산",
    "WEEK_TAG": "2",
    "INOUT_TAG": "2",
    "FL_FLAG": "",
    "DESTSTATION2": "",
    "EXPRESS_YN": "G",
    "BRANCH_LINE": ""
  },
  {
    "LINE_NUM": "05호선",
    "FR_CODE": "551",
    "STATION_CD": "2552",
    "STATION_NM": "명일",
    "TRAIN_NO": "5097",
    "ARRIVETIME": "16:02:40",
    "LEFTTIME": "16:03:10",
    "ORIGINSTATION": "2511",
    "DESTSTATION": "2566",
    "SUBWAYSNAME": "방화",
    "SUBWAYENAME": "하남검단산",
    "WEEK_TAG": "2",
    "INOUT_TAG": "2",
    "FL_FLAG": "",
    "DESTSTATION2": "",
    "EXPRESS_YN": "G",
    "BRANCH_LINE": ""
  },
  {
    "LINE_NUM": "05호선",
    "FR_CODE": "551",
    "STATION_CD": "2552",
    "STATION_NM": "명일",
    "TRAIN_NO": "5099",
    "ARRIVETIME": "16:15:40",
    "LEFTTIME": "16:16:10",
    "ORIGINSTATION": "2511",
    "DESTSTATION": "2566",
    "SUBWAYSNAME": "방화",
    "SUBWAYENAME": "하남검단산",
    "WEEK_TAG": "2",
    "INOUT_TAG": "2",
    "FL_FLAG": "",
    "DESTSTATION2": "",
    "EXPRESS_YN": "G",
    "BRANCH_LINE": ""
  },
  {
    "LINE_NUM": "05호선",
    "FR_CODE": "551",
    "STATION_CD": "2552",
    "STATION_NM": "명일",
    "TRAIN_NO": "5101",
    "ARRIVETIME": "16:28:40",
    "LEFTTIME": "16:29:10",
    "ORIGINSTATION": "2511",
    "DESTSTATION": "2566",
    "SUBWAYSNAME": "방화",
    "SUBWAYENAME": "하남검단산",
    "WEEK_TAG": "2",
    "INOUT_TAG": "2",
    "FL_FLAG": "",
    "DESTSTATION2": "",
    "EXPRESS_YN": "G",
    "BRANCH_LINE": ""
  },
  {
    "LINE_NUM": "05호선",
    "FR_CODE": "551",
    "STATION_CD": "2552",
    "STATION_NM": "명일",
    "TRAIN_NO": "5103",
    "ARRIVETIME": "16:41:40",
    "LEFTTIME": "16:42:10",
    "ORIGINSTATION": "2511",
    "DESTSTATION": "2566",
    "SUBWAYSNAME": "방화",
    "SUBWAYENAME": "하남검단산",
    "WEEK_TAG": "2",
    "INOUT_TAG": "2",
    "FL_FLAG": "",
    "DESTSTATION2": "",
    "EXPRESS_YN": "G",
    "BRANCH_LINE": ""
  },
  {
    "LINE_NUM": "05호선",
    "FR_CODE": "551",
    "STATION_CD": "2552",
    "STATION_NM": "명일",
    "TRAIN_NO": "5105",
    "ARRIVETIME": "16:54:40",
    "LEFTTIME": "16:55:10",
    "ORIGINSTATION": "2511",
    "DESTSTATION": "2566",
    "SUBWAYSNAME": "방화",
    "SUBWAYENAME": "하남검단산",
    "WEEK_TAG": "2",
    "INOUT_TAG": "2",
    "FL_FLAG": "",
    "DESTSTATION2": "",
    "EXPRESS_YN": "G",
    "BRANCH_LINE": ""
  },
  {
    "LINE_NUM": "05호선",
    "FR_CODE": "551",
    "STATION_CD": "2552",
    "STATION_NM": "명일",
    "TRAIN_NO": "5107",
    "ARRIVETIME": "17:07:40",
    "LEFTTIME": "17:08:10",
    "ORIGINSTATION": "2511",
    "DESTSTATION": "2566",
    "SUBWAYSNAME": "방화",
    "SUBWAYENAME": "하남검단산",
    "WEEK_TAG": "2",
    "INOUT_TAG": "2",
    "FL_FLAG": "",
    "DESTSTATION2": "",
    "EXPRESS_YN": "G",
    "BRANCH_LINE": ""
  },
  {
    "LINE_NUM": "05호선",
    "FR_CODE": "551",
    "STATION_CD": "2552",
    "STATION_NM": "명일",
    "TRAIN_NO": "5109",
    "ARRIVETIME": "17:20:40",
    "LEFTTIME": "17:21:10",
    "ORIGINSTATION": "2511",
    "DESTSTATION": "2566",
    "SUBWAYSNAME": "방화",
    "SUBWAYENAME": "하남검단산",
    "WEEK_TAG": "2",
    "INOUT_TAG": "2",
    "FL_FLAG": "",
    "DESTSTATION2": "",
    "EXPRESS_YN": "G",
    "BRANCH_LINE": ""
  },
  {
    "LINE_NUM": "05호선",
    "FR_CODE": "551",
    "STATION_CD": "2552",
    "STATION_NM": "명일",
    "TRAIN_NO": "5111",
    "ARRIVETIME": "17:33:40",
    "LEFTTIME": "17:34:10",
    "ORIGINSTATION": "2511",
    "DESTSTATION": "2566",
    "SUBWAYSNAME": "방화",
    "SUBWAYENAME": "하남검단산",
    "WEEK_TAG": "2",
    "INOUT_TAG": "2",
    "FL_FLAG": "",
    "DESTSTATION2": "",
    "EXPRESS_YN": "G",
    "BRANCH_LINE": ""
  },
  {
    "LINE_NUM": "05호선",
    "FR_CODE": "551",
    "STATION_CD": "2552",
    "STATION_NM": "명일",
    "TRAIN_NO": "5113",
    "ARRIVETIME": "17:46:40",
    "LEFTTIME": "17:47:10",
    "ORIGINSTATION": "2511",
    "DESTSTATION": "2566",
    "SUBWAYSNAME": "방화",
    "SUBWAYENAME": "하남검단산",
    "WEEK_TAG": "2",
    "INOUT_TAG": "2",
    "FL_FLAG": "",
    "DESTSTATION2": "",
    "EXPRESS_YN": "G",
    "BRANCH_LINE": ""
  },
  {
    "LINE_NUM": "05호선",
    "FR_CODE": "551",
    "STATION_CD": "2552",
    "STATION_NM": "명일",
    "TRAIN_NO": "5115",
    "ARRIVETIME": "17:59:40",
    "LEFTTIME": "18:00:10",
    "ORIGINSTATION": "2511",
    "DESTSTATION": "2566",
    "SUBWAYSNAME": "방화",
    "SUBWAYENAME": "하남검단산",
    "WEEK_TAG": "2",
    "INOUT_TAG": "2",
    "FL_FLAG": "",
    "DESTSTATION2": "",
    "EXPRESS_YN": "G",
    "BRANCH_LINE": ""
  },
  {
    "LINE_NUM": "05호선",
    "FR_CODE": "551",
    "STATION_CD": "2552",
    "STATION_NM": "명일",
    "TRAIN_NO": "5117",
    "ARRIVETIME": "18:12:40",
    "LEFTTIME": "18:13:10",
    "ORIGINSTATION": "2511",
    "DESTSTATION": "2566",
    "SUBWAYSNAME": "방화",
    "SUBWAYENAME": "하남검단산",
    "WEEK_TAG": "2",
    "INOUT_TAG": "2",
    "FL_FLAG": "",
    "DESTSTATION2": "",
    "EXPRESS_YN": "G",
    "BRANCH_LINE": ""
  },
  {
    "LINE_NUM": "05호선",
    "FR_CODE": "551",
    "STATION_CD": "2552",
    "STATION_NM": "명일",
    "TRAIN_NO": "5119",
    "ARRIVETIME": "18:25:40",
    "LEFTTIME": "18:26:10",
    "ORIGINSTATION": "2511",
    "DESTSTATION": "2566",
    "SUBWAYSNAME": "방화",
    "SUBWAYENAME": "하남검단산",
    "WEEK_TAG": "2",
    "INOUT_TAG": "2",
    "FL_FLAG": "",
    "DESTSTATION2": "",
    "EXPRESS_YN": "G",
    "BRANCH_LINE": ""
  },
  {
    "LINE_NUM": "05호선",
    "FR_CODE": "551",
    "STATION_CD": "2552",
    "STATION_NM": "명일",
    "TRAIN_NO": "5121",
    "ARRIVETIME": "18:38:40",
    "LEFTTIME": "18:39:10",
    "ORIGINSTATION": "2511",
    "DESTSTATION": "2566",
    "SUBWAYSNAME": "방화",
    "SUBWAYENAME": "하남검단산",
    "WEEK_TAG": "2",
    "INOUT_TAG": "2",
    "FL_FLAG": "",
    "DESTSTATION2": "",
    "EXPRESS_YN": "G",
    "BRANCH_LINE": ""
  },
  {
    "LINE_NUM": "05호선",
    "FR_CODE": "551",
    "STATION_CD": "2552",
    "STATION_NM": "명일",
    "TRAIN_NO": "5123",
    "ARRIVETIME": "18:51:40",
    "LEFTTIME": "18:52:10",
    "ORIGINSTATION": "2511",
    "DESTSTATION": "2566",
    "SUBWAYSNAME": "방화",
    "SUBWAYENAME": "하남검단산",
    "WEEK_TAG": "2",
    "INOUT_TAG": "2",
    "FL_FLAG": "",
    "DESTSTATION2": "",
    "EXPRESS_YN": "G",
    "BRANCH_LINE": ""
  },
  {
    "LINE_NUM": "05호선",
    "FR_CODE": "551",
    "STATION_CD": "2552",
    "STATION_NM": "명일",
    "TRAIN_NO": "5125",
    "ARRIVETIME": "19:04:40",
    "LEFTTIME": "19:05:10",
    "ORIGINSTATION": "2511",
    "DESTSTATION": "2566",
    "SUBWAYSNAME": "방화",
    "SUBWAYENAME": "하남검단산",
    "WEEK_TAG": "2",
    "INOUT_TAG": "2",
    "FL_FLAG": "",
    "DESTSTATION2": "",
    "EXPRESS_YN": "G",
    "BRANCH_LINE": ""
  },
  {
    "LINE_NUM": "05호선",
    "FR_CODE": "551",
    "STATION_CD": "2552",
    "STATION_NM": "명일",
    "TRAIN_NO": "5127",
    "ARRIVETIME": "19:17:40",
    "LEFTTIME": "19:18:10",
    "ORIGINSTATION": "2511",
    "DESTSTATION": "2566",
    "SUBWAYSNAME": "방화",
    "SUBWAYENAME": "하남검단산",
    "WEEK_TAG": "2",
    "INOUT_TAG": "2",
    "FL_FLAG": "",
    "DESTSTATION2": "",
    "EXPRESS_YN": "G",
    "BRANCH_LINE": ""
  },
  {
    "LINE_NUM": "05호선",
    "FR_CODE": "551",
    "STATION_CD": "2552",
    "STATION_NM": "명일",
    "TRAIN_NO": "5129",
    "ARRIVETIME": "19:30:40",
    "LEFTTIME": "19:31:10",
    "ORIGINSTATION": "2511",
    "DESTSTATION": "2566",
    "SUBWAYSNAME": "방화",
    "SUBWAYENAME": "하남검단산",
    "WEEK_TAG": "2",
    "INOUT_TAG": "2",
    "FL_FLAG": "",
    "DESTSTATION2": "",
    "EXPRESS_YN": "G",
    "BRANCH_LINE": ""
  },
  {
    "LINE_NUM": "05호선",
    "FR_CODE": "551",
    "STATION_CD": "2552",
    "STATION_NM": "명일",
    "TRAIN_NO": "5131",
    "ARRIVETIME": "19:43:40",
    "LEFTTIME": "19:44:10",
    "ORIGINSTATION": "2511",
    "DESTSTATION": "2566",
    "SUBWAYSNAME": "방화",
    "SUBWAYENAME": "하남검단산",
    "WEEK_TAG": "2",
    "INOUT_TAG": "2",
    "FL_FLAG": "",
    "DESTSTATION2": "",
    "EXPRESS_YN": "G",
    "BRANCH_LINE": ""
  },
  {
    "LINE_NUM": "05호선",
    "FR_CODE": "551",
    "STATION_CD": "2552",
    "STATION_NM": "명일",
    "TRAIN_NO": "5133",
    "ARRIVETIME": "19:56:40",
    "LEFTTIME": "19:57:10",
    "ORIGINSTATION": "2511",
    "DESTSTATION": "2566",
    "SUBWAYSNAME": "방화",
    "SUBWAYENAME": "하남검단산",
    "WEEK_TAG": "2",
    "INOUT_TAG": "2",
    "FL_FLAG": "",
    "DESTSTATION2": "",
    "EXPRESS_YN": "G",
    "BRANCH_LINE": ""
  },
  {
    "LINE_NUM": "05호선",
    "FR_CODE": "551",
    "STATION_CD": "2552",
    "STATION_NM": "명일",
    "TRAIN_NO": "5135",
    "ARRIVETIME": "20:09:40",
    "LEFTTIME": "20:10:10",
    "ORIGINSTATION": "2511",
    "DESTSTATION": "2566",
    "SUBWAYSNAME": "방화",
    "SUBWAYENAME": "하남검단산",
    "WEEK_TAG": "2",
    "INOUT_TAG": "2",
    "FL_FLAG": "",
    "DESTSTATION2": "",
    "EXPRESS_YN": "G",
    "BRANCH_LINE": ""
  },
  {
    "LINE_NUM": "05호선",
    "FR_CODE": "551",
    "STATION_CD": "2552",
    "STATION_NM": "명일",
    "TRAIN_NO": "5137",
    "ARRIVETIME": "20:22:40",
    "LEFTTIME": "20:23:10",
    "ORIGINSTATION": "2511",
    "DESTSTATION": "2566",
    "SUBWAYSNAME": "방화",
    "SUBWAYENAME": "하남검단산",
    "WEEK_TAG": "2",
    "INOUT_TAG": "2",
    "FL_FLAG": "",
    "DESTSTATION2": "",
    "EXPRESS_YN": "G",
    "BRANCH_LINE": ""
  },
  {
    "LINE_NUM": "05호선",
    "FR_CODE": "551",
    "STATION_CD": "2552",
    "STATION_NM": "명일",
    "TRAIN_NO": "5139",
    "ARRIVETIME": "20:35:40",
    "LEFTTIME": "20:36:10",
    "ORIGINSTATION": "2511",
    "DESTSTATION": "2566",
    "SUBWAYSNAME": "방화",
    "SUBWAYENAME": "하남검단산",
    "WEEK_TAG": "2",
    "INOUT_TAG": "2",
    "FL_FLAG": "",
    "DESTSTATION2": "",
    "EXPRESS_YN": "G",
    "BRANCH_LINE": ""
  },
  {
    "LINE_NUM": "05호선",
    "FR_CODE": "551",
    "STATION_CD": "2552",
    "STATION_NM": "명일",
    "TRAIN_NO": "5141",
    "ARRIVETIME": "20:48:40",
    "LEFTTIME": "20:49:10",
    "ORIGINSTATION": "2511",
    "DESTSTATION": "2566",
    "SUBWAYSNAME": "방화",
    "SUBWAYENAME": "하남검단산",
    "WEEK_TAG": "2",
    "INOUT_TAG": "2",
    "FL_FLAG": "",
    "DESTSTATION2": "",
    "EXPRESS_YN": "G",
    "BRANCH_LINE": ""
  },
  {
    "LINE_NUM": "05호선",
    "FR_CODE": "551",
    "STATION_CD": "2552",
    "STATION_NM": "명일",
    "TRAIN_NO": "5143",
    "ARRIVETIME": "21:01:40",
    "LEFTTIME": "21:02:10",
    "ORIGINSTATION": "2511",
    "DESTSTATION": "2566",
    "SUBWAYSNAME": "방화",
    "SUBWAYENAME": "하남검단산",
    "WEEK_TAG": "2",
    "INOUT_TAG": "2",
    "FL_FLAG": "",
    "DESTSTATION2": "",
    "EXPRESS_YN": "G",
    "BRANCH_LINE": ""
  },
  {
    "LINE_NUM": "05호선",
    "FR_CODE": "551",
    "STATION_CD": "2552",
    "STATION_NM": "명일",
    "TRAIN_NO": "5145",
    "ARRIVETIME": "21:14:40",
    "LEFTTIME": "21:15:10",
    "ORIGINSTATION": "2511",
    "DESTSTATION": "2566",
    "SUBWAYSNAME": "방화",
    "SUBWAYENAME": "하남검단산",
    "WEEK_TAG": "2",
    "INOUT_TAG": "2",
    "FL_FLAG": "",
    "DESTSTATION2": "",
    "EXPRESS_YN": "G",
    "BRANCH_LINE": ""
  },
  {
    "LINE_NUM": "05호선",
    "FR_CODE": "551",
    "STATION_CD": "2552",
    "STATION_NM": "명일",
    "TRAIN_NO": "5147",
    "ARRIVETIME": "21:27:40",
    "LEFTTIME": "21:28:10",
    "ORIGINSTATION": "2511",
    "DESTSTATION": "2566",
    "SUBWAYSNAME": "방화",
    "SUBWAYENAME": "하남검단산",
    "WEEK_TAG": "2",
    "INOUT_TAG": "2",
    "FL_FLAG": "",
    "DESTSTATION2": "",
    "EXPRESS_YN": "G",
    "BRANCH_LINE": ""
  },
  {
    "LINE_NUM": "05호선",
    "FR_CODE": "551",
    "STATION_CD": "2552",
    "STATION_NM": "명일",
    "TRAIN_NO": "5149",
    "ARRIVETIME": "21:40:40",
    "LEFTTIME": "21:41:10",
    "ORIGINSTATION": "2511",
    "DESTSTATION": "2566",
    "SUBWAYSNAME": "방화",
    "SUBWAYENAME": "하남검단산",
    "WEEK_TAG": "2",
    "INOUT_TAG": "2",
    "FL_FLAG": "",
    "DESTSTATION2": "",
    "EXPRESS_YN": "G",
    "BRANCH_LINE": ""
  },
  {
    "LINE_NUM": "05호선",
    "FR_CODE": "551",
    "STATION_CD": "2552",
    "STATION_NM": "명일",
    "TRAIN_NO": "5151",
    "ARRIVETIME": "21:53:40",
    "LEFTTIME": "21:54:10",
    "ORIGINSTATION": "2511",
    "DESTSTATION": "2566",
    "SUBWAYSNAME": "방화",
    "SUBWAYENAME": "하남검단산",
    "WEEK_TAG": "2",
    "INOUT_TAG": "2",
    "FL_FLAG": "",
    "DESTSTATION2": "",
    "EXPRESS_YN": "G",
    "BRANCH_LINE": ""
  },
  {
    "LINE_NUM": "05호선",
    "FR_CODE": "551",
    "STATION_CD": "2552",
    "STATION_NM": "명일",
    "TRAIN_NO": "5153",
    "ARRIVETIME": "22:06:40",
    "LEFTTIME": "22:07:10",
    "ORIGINSTATION": "2511",
    "DESTSTATION": "2566",
    "SUBWAYSNAME": "방화",
    "SUBWAYENAME": "하남검단산",
    "WEEK_TAG": "2",
    "INOUT_TAG": "2",
    "FL_FLAG": "",
    "DESTSTATION2": "",
    "EXPRESS_YN": "G",
    "BRANCH_LINE": ""
  },
  {
    "LINE_NUM": "05호선",
    "FR_CODE": "551",
    "STATION_CD": "2552",
    "STATION_NM": "명일",
    "TRAIN_NO": "5155",
    "ARRIVETIME": "22:19:40",
    "LEFTTIME": "22:20:10",
    "ORIGINSTATION": "2511",
    "DESTSTATION": "2566",
    "SUBWAYSNAME": "방화",
    "SUBWAYENAME": "하남검단산",
    "WEEK_TAG": "2",
    "INOUT_TAG": "2",
    "FL_FLAG": "",
    "DESTSTATION2": "",
    "EXPRESS_YN": "G",
    "BRANCH_LINE": ""
  },
  {
    "LINE_NUM": "05호선",
    "FR_CODE": "551",
    "STATION_CD": "2552",
    "STATION_NM": "명일",
    "TRAIN_NO": "5157",
    "ARRIVETIME": "22:32:40",
    "LEFTTIME": "22:33:10",
    "ORIGINSTATION": "2511",
    "DESTSTATION": "2566",
    "SUBWAYSNAME": "방화",
    "SUBWAYENAME": "하남검단산",
    "WEEK_TAG": "2",
    "INOUT_TAG": "2",
    "FL_FLAG": "",
    "DESTSTATION2": "",
    "EXPRESS_YN": "G",
    "BRANCH_LINE": ""
  },
  {
    "LINE_NUM": "05호선",
    "FR_CODE": "551",
    "STATION_CD": "2552",
    "STATION_NM": "명일",
    "TRAIN_NO": "5159",
    "ARRIVETIME": "22:45:40",
    "LEFTTIME": "22:46:10",
    "ORIGINSTATION": "2511",
    "DESTSTATION": "2566",
    "SUBWAYSNAME": "방화",
    "SUBWAYENAME": "하남검단산",
    "WEEK_TAG": "2",
    "INOUT_TAG": "2",
    "FL_FLAG": "",
    "DESTSTATION2": "",
    "EXPRESS_YN": "G",
    "BRANCH_LINE": ""
  },
  {
    "LINE_NUM": "05호선",
    "FR_CODE": "551",
    "STATION_CD": "2552",
    "STATION_NM": "명일",
    "TRAIN_NO": "5161",
    "ARRIVETIME": "22:59:10",
    "LEFTTIME": "22:59:40",
    "ORIGINSTATION": "2511",
    "DESTSTATION": "2566",
    "SUBWAYSNAME": "방화",
    "SUBWAYENAME": "하남검단산",
    "WEEK_TAG": "2",
    "INOUT_TAG": "2",
    "FL_FLAG": "",
    "DESTSTATION2": "",
    "EXPRESS_YN": "G",
    "BRANCH_LINE": ""
  },
  {
    "LINE_NUM": "05호선",
    "FR_CODE": "551",
    "STATION_CD": "2552",
    "STATION_NM": "명일",
    "TRAIN_NO": "5163",
    "ARRIVETIME": "23:14:10",
    "LEFTTIME": "23:14:40",
    "ORIGINSTATION": "2511",
    "DESTSTATION": "2566",
    "SUBWAYSNAME": "방화",
    "SUBWAYENAME": "하남검단산",
    "WEEK_TAG": "2",
    "INOUT_TAG": "2",
    "FL_FLAG": "",
    "DESTSTATION2": "",
    "EXPRESS_YN": "G",
    "BRANCH_LINE": ""
  },
  {
    "LINE_NUM": "05호선",
    "FR_CODE": "551",
    "STATION_CD": "2552",
    "STATION_NM": "명일",
    "TRAIN_NO": "5165",
    "ARRIVETIME": "23:29:40",
    "LEFTTIME": "23:30:10",
    "ORIGINSTATION": "2511",
    "DESTSTATION": "2554",
    "SUBWAYSNAME": "방화",
    "SUBWAYENAME": "상일동",
    "WEEK_TAG": "2",
    "INOUT_TAG": "2",
    "FL_FLAG": "",
    "DESTSTATION2": "",
    "EXPRESS_YN": "G",
    "BRANCH_LINE": ""
  },
  {
    "LINE_NUM": "05호선",
    "FR_CODE": "551",
    "STATION_CD": "2552",
    "STATION_NM": "명일",
    "TRAIN_NO": "5167",
    "ARRIVETIME": "23:45:40",
    "LEFTTIME": "23:46:10",
    "ORIGINSTATION": "2511",
    "DESTSTATION": "2566",
    "SUBWAYSNAME": "방화",
    "SUBWAYENAME": "하남검단산",
    "WEEK_TAG": "2",
    "INOUT_TAG": "2",
    "FL_FLAG": "",
    "DESTSTATION2": "",
    "EXPRESS_YN": "G",
    "BRANCH_LINE": ""
  },
  {
    "LINE_NUM": "05호선",
    "FR_CODE": "551",
    "STATION_CD": "2552",
    "STATION_NM": "명일",
    "TRAIN_NO": "5169",
    "ARRIVETIME": "24:03:10",
    "LEFTTIME": "24:03:40",
    "ORIGINSTATION": "2511",
    "DESTSTATION": "2554",
    "SUBWAYSNAME": "방화",
    "SUBWAYENAME": "상일동",
    "WEEK_TAG": "2",
    "INOUT_TAG": "2",
    "FL_FLAG": "",
    "DESTSTATION2": "",
    "EXPRESS_YN": "G",
    "BRANCH_LINE": ""
  },
  {
    "LINE_NUM": "05호선",
    "FR_CODE": "551",
    "STATION_CD": "2552",
    "STATION_NM": "명일",
    "TRAIN_NO": "5171",
    "ARRIVETIME": "24:11:10",
    "LEFTTIME": "24:11:40",
    "ORIGINSTATION": "2511",
    "DESTSTATION": "2554",
    "SUBWAYSNAME": "방화",
    "SUBWAYENAME": "상일동",
    "WEEK_TAG": "2",
    "INOUT_TAG": "2",
    "FL_FLAG": "",
    "DESTSTATION2": "",
    "EXPRESS_YN": "G",
    "BRANCH_LINE": ""
  }
]